MANIFEST.in
NEWS.txt
README.rst
setup.py
src/docsix/__init__.py
src/docsix/testcode.py
src/docsix/unicode_output.py
src/docsix.egg-info/PKG-INFO
src/docsix.egg-info/SOURCES.txt
src/docsix.egg-info/dependency_links.txt
src/docsix.egg-info/not-zip-safe
src/docsix.egg-info/requires.txt
src/docsix.egg-info/top_level.txt