Metadata-Version: 1.0
Name: docsix
Version: 0.1
Summary: Doctests on Python 2 & 3
Home-page: UNKNOWN
Author: Nathan R. Yergler
Author-email: nathan@yergler.net
License: UNKNOWN
Keywords: testing doctest
Platform: UNKNOWN
